bfportal_grpc_bf6/__init__.py
bfportal_grpc_bf6/access_token.py
bfportal_grpc_bf6/converter.py
bfportal_grpc_bf6/helpers/__init__.py
bfportal_grpc_bf6/helpers/compile.py
bfportal_grpc_bf6/proto/__init__.py
bfportal_grpc_bf6/proto/authentication_pb2.py
bfportal_grpc_bf6/proto/authentication_pb2.pyi
bfportal_grpc_bf6/proto/authentication_pb2_grpc.py
bfportal_grpc_bf6/proto/localization_pb2.py
bfportal_grpc_bf6/proto/localization_pb2.pyi
bfportal_grpc_bf6/proto/localization_pb2_grpc.py
bfportal_grpc_bf6/proto/play_pb2.py
bfportal_grpc_bf6/proto/play_pb2.pyi
bfportal_grpc_bf6/proto/play_pb2_grpc.py
bfportal_grpc_bf6/proto/reporting_pb2.py
bfportal_grpc_bf6/proto/reporting_pb2.pyi
bfportal_grpc_bf6/proto/reporting_pb2_grpc.py
bfportal_grpc_bf6-0.1.9.dist-info/METADATA
bfportal_grpc_bf6-0.1.9.dist-info/WHEEL
bfportal_grpc_bf6-0.1.9.dist-info/entry_points.txt
bfportal_grpc_bf6-0.1.9.dist-info/licenses/LICENSE
bfportal_grpc_bf6-0.1.9.dist-info/RECORD
