Metadata-Version: 2.4
Name: bfportal_grpc_bf6
Version: 0.1.9
Summary: bf6 portal web grpc as python package 
License-File: LICENSE
Keywords: bfportal,grpc,Battlefield portal
Author: iiTzArcur
Author-email: arcur@gametools.network
Requires-Python: >=3.10,<4.0
Classifier: Programming Language :: Python
Classifier: Programming Language :: Python :: 3
Classifier: Programming Language :: Python :: 3.10
Classifier: Programming Language :: Python :: 3.11
Classifier: Programming Language :: Python :: 3.12
Classifier: Programming Language :: Python :: 3.13
Classifier: Programming Language :: Python :: 3.14
Requires-Dist: aiohttp (>=3.13.0,<4.0.0)
Requires-Dist: grpcio (>=1.75.1,<2.0.0)
Requires-Dist: httpcore[asyncio,http2] (>=1.0.9,<2.0.0)
Requires-Dist: proto-compile (>=0.1.7,<0.2.0)
Requires-Dist: protobuf (>=6.32.1,<7.0.0)
Requires-Dist: python-dotenv (>=1.1.1,<2.0.0)
Project-URL: Bug Tracker, https://github.com/community-network/bfportal-grpc-bf6/issues
Project-URL: Repository, https://github.com/community-network/bfportal-grpc-bf6
